django_postgresql_ws/__init__.py
django_postgresql_ws/base.py
django_postgresql_ws/client.py
django_postgresql_ws/creation.py
django_postgresql_ws/features.py
django_postgresql_ws/introspection.py
django_postgresql_ws/operations.py
django_postgresql_ws/schema.py
django_postgresql_ws-0.1.0.dist-info/LICENSE
django_postgresql_ws-0.1.0.dist-info/WHEEL
django_postgresql_ws-0.1.0.dist-info/METADATA
django_postgresql_ws-0.1.0.dist-info/RECORD
