Metadata-Version: 2.1
Name: django-postgresql-ws
Version: 0.1.0
Summary: Django PostgreSQL backend proxied over WebSockets (for WASM)
Home-page: https://github.com/SubstructureOne/django-postgresql-ws
License: BSD-3-Clause
Author: dek
Author-email: dek@substructure.one
Requires-Python: >=3.8,<4.0
Classifier: Environment :: Web Environment
Classifier: Framework :: AsyncIO
Classifier: Framework :: Django
Classifier: License :: OSI Approved :: BSD License
Classifier: Programming Language :: Python
Classifier: Programming Language :: Python :: 3
Classifier: Programming Language :: Python :: 3.8
Classifier: Programming Language :: Python :: 3.9
Classifier: Programming Language :: Python :: 3.10
Classifier: Programming Language :: Python :: 3.11
Classifier: Programming Language :: Python :: 3
Classifier: Topic :: Internet :: WWW/HTTP :: Browsers
Requires-Dist: asgiref (>=3.5.2,<4.0.0)
Requires-Dist: django (>=4.1.3,<5.0.0)
Requires-Dist: pgwasm (>=0.2.1,<0.3.0)
Project-URL: Repository, https://github.com/SubstructureOne/django-postgresql-ws
